adafruit_ble_eddystone/__init__.py
adafruit_ble_eddystone/uid.py
adafruit_ble_eddystone/url.py
adafruit_circuitpython_ble_eddystone-1.10.23.dist-info/licenses/LICENSE
adafruit_circuitpython_ble_eddystone-1.10.23.dist-info/METADATA
adafruit_circuitpython_ble_eddystone-1.10.23.dist-info/WHEEL
adafruit_circuitpython_ble_eddystone-1.10.23.dist-info/top_level.txt
adafruit_circuitpython_ble_eddystone-1.10.23.dist-info/RECORD
