Metadata-Version: 2.4
Name: adafruit-circuitpython-ble-eddystone
Version: 1.10.23
Summary: CircuitPython BLE library for Google's open 'physical web' Eddystone.
Author-email: Adafruit Industries <circuitpython@adafruit.com>
License: MIT
Project-URL: Homepage, https://github.com/adafruit/Adafruit_CircuitPython_BLE_Eddystone
Keywords: adafruit,blinka,circuitpython,micropython,ble_eddystone,eddystone,ble
Classifier: Intended Audience :: Developers
Classifier: Topic :: Software Development :: Libraries
Classifier: Topic :: Software Development :: Embedded Systems
Classifier: Topic :: System :: Hardware
Classifier: License :: OSI Approved :: MIT License
Classifier: Programming Language :: Python :: 3
License-File: LICENSE
Requires-Dist: Adafruit-Blinka
Requires-Dist: adafruit-circuitpython-ble>=8.0.0
Provides-Extra: optional
Dynamic: license-file
